mylib_036/__init__.py
mylib1_036-0.1.dist-info/LICENSE.txt
mylib1_036-0.1.dist-info/METADATA
mylib1_036-0.1.dist-info/WHEEL
mylib1_036-0.1.dist-info/top_level.txt
mylib1_036-0.1.dist-info/RECORD
